topsis_VAIBHAV/__init__.py
topsis_VAIBHAV/topsis.py
Topsis_vaibhav_tandon_102203877-1.0.1.dist-info/LICENSE
Topsis_vaibhav_tandon_102203877-1.0.1.dist-info/METADATA
Topsis_vaibhav_tandon_102203877-1.0.1.dist-info/WHEEL
Topsis_vaibhav_tandon_102203877-1.0.1.dist-info/entry_points.txt
Topsis_vaibhav_tandon_102203877-1.0.1.dist-info/top_level.txt
Topsis_vaibhav_tandon_102203877-1.0.1.dist-info/RECORD
