Metadata-Version: 2.1
Name: Topsis-vaibhav-tandon-102203877
Version: 1.0.1
Summary: A Python package for implementing the TOPSIS (Technique for Order of Preference by Similarity to Ideal Solution) method in Multi-Criteria Decision Making (MCDM)
Author: VAIBHAV_TANDON
Author-email: vtandon_be22@thapar.edu
Classifier: Programming Language :: Python :: 3
Classifier: License :: OSI Approved :: MIT License
Classifier: Operating System :: OS Independent
License-File: LICENSE
Requires-Dist: numpy
Requires-Dist: pandas
